goose/__init__.py
goose/app.py
goose/cli.py
goose/chatting/__init__.py
goose/chatting/store.py
goose/chatting/api/__init__.py
goose/chatting/api/router.py
goose/chatting/api/schema.py
goose/chatting/api/streaming.py
goose/core/__init__.py
goose/core/app.py
goose/core/config.py
goose/core/loader.py
goose/core/reload.py
goose/core/websocket.py
goose/scaffolding/__init__.py
goose/scaffolding/cli.py
goose/scaffolding/template/__init__.py
goose/scaffolding/template/app.py
goose/scaffolding/template/conftest.py
goose/scaffolding/template/tests/__init__.py
goose/scaffolding/template/tests/test_example.py
goose/testing/__init__.py
goose/testing/cli.py
goose/testing/discovery.py
goose/testing/engine.py
goose/testing/errors.py
goose/testing/exceptions.py
goose/testing/fixtures.py
goose/testing/hooks.py
goose/testing/output.py
goose/testing/runner.py
goose/testing/test_case.py
goose/testing/validator.py
goose/testing/api/__init__.py
goose/testing/api/exceptions.py
goose/testing/api/persistence.py
goose/testing/api/router.py
goose/testing/api/schema.py
goose/testing/api/jobs/__init__.py
goose/testing/api/jobs/enums.py
goose/testing/api/jobs/exceptions.py
goose/testing/api/jobs/job_notifier.py
goose/testing/api/jobs/job_queue.py
goose/testing/api/jobs/job_target_resolver.py
goose/testing/api/jobs/models.py
goose/testing/api/jobs/state.py
goose/testing/models/__init__.py
goose/testing/models/messages.py
goose/testing/models/tests.py
goose/tooling/__init__.py
goose/tooling/executor.py
goose/tooling/schema.py
goose/tooling/api/__init__.py
goose/tooling/api/router.py
goose/tooling/api/schema.py
gooseapp/__init__.py
gooseapp/app.py
gooseapp/conftest.py
gooseapp/tests/__init__.py
gooseapp/tests/test_agent_behaviour_basic.py
gooseapp/tests/test_agent_behaviour_failures.py
gooseapp/tests/test_agent_behaviour_workflows.py
llm_goose-0.1.33.dist-info/licenses/LICENSE
llm_goose-0.1.33.dist-info/METADATA
llm_goose-0.1.33.dist-info/WHEEL
llm_goose-0.1.33.dist-info/entry_points.txt
llm_goose-0.1.33.dist-info/top_level.txt
llm_goose-0.1.33.dist-info/RECORD
