Metadata-Version: 2.4
Name: llm-goose
Version: 0.1.33
Summary: LLM testing framework for validating agent behavior and tool usage
Author-email: Rafał Łazicki <rafal.lazicki99@gmail.com>
License-Expression: MIT
Project-URL: Homepage, https://github.com/Raff-dev/goose
Project-URL: Repository, https://github.com/Raff-dev/goose
Project-URL: Issues, https://github.com/Raff-dev/goose/issues
Project-URL: Documentation, https://github.com/Raff-dev/goose#readme
Keywords: llm,testing,agent,langchain,openai,pytest,ai,framework
Classifier: Development Status :: 3 - Alpha
Classifier: Intended Audience :: Developers
Classifier: Operating System :: OS Independent
Classifier: Programming Language :: Python :: 3
Classifier: Programming Language :: Python :: 3.13
Classifier: Topic :: Software Development :: Testing
Classifier: Topic :: Software Development :: Libraries :: Python Modules
Classifier: Topic :: Scientific/Engineering :: Artificial Intelligence
Classifier: Topic :: Internet :: WWW/HTTP :: HTTP Servers
Classifier: Environment :: Console
Classifier: Environment :: Web Environment
Requires-Python: >=3.13
License-File: LICENSE
Requires-Dist: fastapi>=0.115.0
Requires-Dist: langchain>=1.0.4
Requires-Dist: langchain-openai>=0.1.0
Requires-Dist: openai>=2.7.1
Requires-Dist: pydantic>=2.12.4
Requires-Dist: python-dotenv>=1.0.1
Requires-Dist: typer>=0.12.5
Requires-Dist: uvicorn>=0.32.0
Requires-Dist: websockets>=15.0.1
Dynamic: license-file
